LICENSE.txt
MANIFEST.in
README.MD
setup.py
SPMUtil/DataSerializer.py
SPMUtil/DataSerializerPackage.py
SPMUtil/__init__.py
SPMUtil/converter.py
SPMUtil/flatten.py
SPMUtil.egg-info/PKG-INFO
SPMUtil.egg-info/SOURCES.txt
SPMUtil.egg-info/dependency_links.txt
SPMUtil.egg-info/requires.txt
SPMUtil.egg-info/top_level.txt
SPMUtil/analyzer/BaseAnalyzer.py
SPMUtil/analyzer/DulcineaAnalyzer.py
SPMUtil/analyzer/GridAnalyzer.py
SPMUtil/analyzer/SxmAnalyzer.py
SPMUtil/analyzer/__init__.py
SPMUtil/cython_files/__init__.py
SPMUtil/cython_files/cython_code.cp36-win_amd64.pyd
SPMUtil/cython_files/cython_pyx_code.c
SPMUtil/cython_files/cython_pyx_code.pyx
SPMUtil/cython_files/cython_setup.py
SPMUtil/cython_files/cython_template_matching_code.c
SPMUtil/cython_files/cython_template_matching_code.pyx
SPMUtil/cython_files/cython_tm_code.cp36-win_amd64.pyd
SPMUtil/cython_files/template_matching.c
SPMUtil/cython_files/template_matching.h
SPMUtil/filters/filter_1d.py
SPMUtil/filters/filter_2d.py
SPMUtil/formula/__init__.py
SPMUtil/formula/_math_formula.py
SPMUtil/formula/_physic_formula.py
SPMUtil/formula/_spm_common_formula.py
SPMUtil/gui/JsonEditor.py
SPMUtil/gui/NanonisGridVisualizer.py
SPMUtil/gui/__init__.py
SPMUtil/gui/line_selector.py
SPMUtil/gui/point_selector.py
SPMUtil/gui/rect_2d_selector.py
SPMUtil/gui/tilt_calculator.py
SPMUtil/nanonispy/__init__.py
SPMUtil/nanonispy/constants.py
SPMUtil/nanonispy/read.py
SPMUtil/structures/__init__.py
SPMUtil/structures/_structures.py
SPMUtil/structures/point.py
SPMUtil/structures/rect_2d.py
SPMUtil/structures/scan_data_format.py