Metadata-Version: 2.1
Name: SPMUtil
Version: 0.3.15
Summary: Some Common method for SPM data analysis and realtime data processing.
Author: ZHUO DIAO
Author-email: enzian0515@gmail.com
License: LGPL
License-File: LICENSE.txt
